saywhen/__init__.py
saywhen/notification.py
saywhen/audio/142608__autistic-lucario__error.wav
saywhen/audio/80921__justinbw__buttonchime02up.wav
saywhen-0.0.2.data/scripts/saywhen
saywhen-0.0.2.dist-info/LICENSE
saywhen-0.0.2.dist-info/METADATA
saywhen-0.0.2.dist-info/WHEEL
saywhen-0.0.2.dist-info/top_level.txt
saywhen-0.0.2.dist-info/RECORD
