Metadata-Version: 2.1
Name: saywhen
Version: 0.0.2
Summary: Send notifications when command line job finishes
Home-page: https://github.com/yunqing/saywhen
Author: Yunqing Gong
Author-email: gongyq10@gmail.com
License: UNKNOWN
Platform: UNKNOWN
Classifier: Programming Language :: Python :: 3
Classifier: License :: OSI Approved :: MIT License
Classifier: Operating System :: OS Independent
Requires-Python: >=3.5
